foldex/__init__.py
foldex/tcp_server.py
foldex-0.0.3.dist-info/LICENSE
foldex-0.0.3.dist-info/METADATA
foldex-0.0.3.dist-info/WHEEL
foldex-0.0.3.dist-info/top_level.txt
foldex-0.0.3.dist-info/RECORD
