Metadata-Version: 2.1
Name: foldex
Version: 0.0.3
Summary: File Sever written with Python's Asyncio
Home-page: https://github.com/joegasewicz/foldex
Author: Joe Gasewicz
Author-email: joegasewicz@gmail.com
License: UNKNOWN
Platform: UNKNOWN
Classifier: Programming Language :: Python :: 3
Classifier: Programming Language :: Python :: 3.6
Classifier: Programming Language :: Python :: 3.7
Classifier: Programming Language :: Python :: 3.8
Classifier: License :: OSI Approved :: GNU General Public License v3 or later (GPLv3+)
Classifier: Operating System :: OS Independent
